bookmap/__init__.py
bookmap/bookmap.py
bookmap/dto.py
bookmap/sortedcontainers/__init__.py
bookmap/sortedcontainers/sorteddict.py
bookmap/sortedcontainers/sortedlist.py
bookmap/sortedcontainers/sortedset.py
bookmap-0.1.2.dist-info/METADATA
bookmap-0.1.2.dist-info/WHEEL
bookmap-0.1.2.dist-info/licenses/LICENSE
bookmap-0.1.2.dist-info/RECORD
