Metadata-Version: 2.3
Name: bookmap
Version: 0.1.2
Summary: Python implementation of L1 API library
Project-URL: Homepage, https://bookmap.com
Project-URL: Documentation, https://github.com/BookmapAPI/python-api
Project-URL: Source, https://github.com/BookmapAPI/python-api
Author-email: Mykyta Leonov <mykytal@bookmap.com>, Rok Povsik <rokp@bookmap.com>, Roman Pavlenko <romanp@bookmap.com>
Maintainer-email: Roman Pavlenko <romanp@bookmap.com>
License-File: LICENSE
Keywords: api,bookmap,trading
Classifier: License :: OSI Approved :: MIT License
Classifier: Operating System :: OS Independent
Classifier: Programming Language :: Python :: 3
Requires-Python: >=3.6
